{"content": {"suites": {"0": {"status": {"total_pass": 0, "total_skip": 0, "total_xpass": 0, "total_xfail": 0, "total_rerun": 0, "total_fail": 0, "total_error": 1}, "tests": {"0": {"status": "ERROR", "message": "@pytest.fixture()\n    def setup():\n        serv_obj = Service(\"C:/Users/islomdev/Downloads/chromedriver_win32/chromedriver.exe\")\n>       driver = webdriver.Chrome(service=serv_obj)\nE       TypeError: WebDriver.__init__() got an unexpected keyword argument 'service'\n\nconftest.py:9: TypeError\n", "test_name": "test_customer_reg", "rerun": "0"}}, "suite_name": "test_001_CustomerRegistration.py"}}}, "date": "August 17, 2023", "start_time": 1692287625.75965, "total_suite": 1, "status": "FAIL", "status_list": {"pass": "0", "fail": "0", "skip": "0", "error": "1", "xpass": "0", "xfail": "0", "rerun": "0"}, "total_tests": "1"}